dqm_ml_pipeline/__init__.py
dqm_ml_pipeline/_version_.py
dqm_ml_pipeline/cli.py
dqm_ml_pipeline/duckdb_subsets.py
dqm_ml_pipeline/pipeline.py
dqm_ml_pipeline/py.typed
dqm_ml_pipeline/dataloaders/__init__.py
dqm_ml_pipeline/dataloaders/pandas.py
dqm_ml_pipeline/dataloaders/parquet.py
dqm_ml_pipeline/outputwriter/__init__.py
dqm_ml_pipeline/outputwriter/parquet.py
dqm_ml_pipeline-1.1.4.dist-info/METADATA
dqm_ml_pipeline-1.1.4.dist-info/WHEEL
dqm_ml_pipeline-1.1.4.dist-info/entry_points.txt
dqm_ml_pipeline-1.1.4.dist-info/top_level.txt
dqm_ml_pipeline-1.1.4.dist-info/RECORD
